{
    "feature_name": "SALE ORDERS CREATION",
    "user_story": {
        "as_a": "",
        "i_want": "",
        "so_that": "",
        "scenarios": [
            {
                "givens_list": [
                    [
                        "I need a \"sale.order\" with name: SO013 and oid: scenario.anglosaxon_SO013",
                        "having:"
                    ],
                    [
                        "I need a \"sale.order.line\" with oid: scenario.anglosaxon_SO013_line1",
                        "having:"
                    ]
                ],
                "whens_list": [],
                "thens_list": []
            }
        ]
    }
}